canton/__init__.py
canton/cans.py
canton/cans2.py
canton/misc.py
canton/objectives.py
canton-0.1.22.dist-info/DESCRIPTION.rst
canton-0.1.22.dist-info/METADATA
canton-0.1.22.dist-info/RECORD
canton-0.1.22.dist-info/WHEEL
canton-0.1.22.dist-info/metadata.json
canton-0.1.22.dist-info/top_level.txt
