Metadata-Version: 2.0
Name: canton
Version: 0.1.22
Summary: Light-weight TensorFlow Wrapper
Home-page: https://github.com/ctmakro/canton
Author: Qin Yongliang
Author-email: ctmakro@gmail.com
License: MIT
Requires-Dist: numpy
Requires-Dist: tensorflow
